helpers_to_python-2.2.dist-info/licenses/LICENCE
mypackage/__init__.py
mypackage/connect.py
mypackage/print.py
mypackage/search ip.py
mypackage/webattack.py
mypackage/packets/__init__.py
mypackage/packets/connect.py
mypackage/packets/print.py
mypackage/packets/webattack.py
helpers_to_python-2.2.dist-info/METADATA
helpers_to_python-2.2.dist-info/WHEEL
helpers_to_python-2.2.dist-info/top_level.txt
helpers_to_python-2.2.dist-info/RECORD
